random_walk_controversy/__init__.py
random_walk_controversy/__main__.py
random_walk_controversy/rwc.py
random_walk_controversy-0.1.5.dist-info/METADATA
random_walk_controversy-0.1.5.dist-info/LICENSE
random_walk_controversy-0.1.5.dist-info/WHEEL
random_walk_controversy-0.1.5.dist-info/RECORD
