Metadata-Version: 2.1
Name: random-walk-controversy
Version: 0.1.5
Summary: Parallel implementation of Garimella's algorithm to get the RWC score of a network
Home-page: https://github.com/bendico765/random_walk_controversy
License: BSD-2-Clause
Author: Gianluca Morcaldi
Author-email: bendico765@gmail.com
Requires-Python: >=3.7,<4.0
Classifier: License :: OSI Approved :: BSD License
Classifier: Programming Language :: Python :: 3
Classifier: Programming Language :: Python :: 3.7
Classifier: Programming Language :: Python :: 3.8
Classifier: Programming Language :: Python :: 3.9
Classifier: Programming Language :: Python :: 3.10
Classifier: Programming Language :: Python :: 3.11
Requires-Dist: networkx (>=2.3.0,<3.0.0)
Project-URL: Repository, https://github.com/bendico765/random_walk_controversy
